[
  {
    "date": "فيفري 26، 2026",
    "visits": 1123,
    "diff": 1
  },
  {
    "date": "فيفري 27، 2026",
    "visits": 1126,
    "diff": 3
  },
  {
    "date": "فيفري 28، 2026",
    "visits": 1134,
    "diff": 8
  },
  {
    "date": "مارس 01، 2026",
    "visits": 1142,
    "diff": 8
  },
  {
    "date": "مارس 02، 2026",
    "visits": 1144,
    "diff": 2
  },
  {
    "date": "مارس 03، 2026",
    "visits": 1150,
    "diff": 6
  },
  {
    "date": "مارس 04، 2026",
    "visits": 1153,
    "diff": 3
  },
  {
    "date": "مارس 05، 2026",
    "visits": 1161,
    "diff": 8
  },
  {
    "date": "مارس 06، 2026",
    "visits": 1173,
    "diff": 12
  },
  {
    "date": "مارس 07، 2026",
    "visits": 1185,
    "diff": 12
  },
  {
    "date": "مارس 08، 2026",
    "visits": 1188,
    "diff": 3
  },
  {
    "date": "مارس 09، 2026",
    "visits": 1198,
    "diff": 10
  },
  {
    "date": "مارس 10، 2026",
    "visits": 1202,
    "diff": 4
  },
  {
    "date": "مارس 11، 2026",
    "visits": 1209,
    "diff": 7
  },
  {
    "date": "مارس 12، 2026",
    "visits": 1217,
    "diff": 8
  },
  {
    "date": "مارس 13، 2026",
    "visits": 1232,
    "diff": 15
  },
  {
    "date": "مارس 14، 2026",
    "visits": 1237,
    "diff": 5
  },
  {
    "date": "مارس 15، 2026",
    "visits": 1242,
    "diff": 5
  },
  {
    "date": "مارس 18، 2026",
    "visits": 1255,
    "diff": 13
  },
  {
    "date": "مارس 19، 2026",
    "visits": 1261,
    "diff": 6
  },
  {
    "date": "مارس 23، 2026",
    "visits": 1347,
    "diff": 86
  },
  {
    "date": "مارس 24، 2026",
    "visits": 1352,
    "diff": 5
  },
  {
    "date": "مارس 25، 2026",
    "visits": 1372,
    "diff": 20
  },
  {
    "date": "مارس 26، 2026",
    "visits": 1409,
    "diff": 37
  },
  {
    "date": "مارس 27، 2026",
    "visits": 1424,
    "diff": 15
  },
  {
    "date": "مارس 28، 2026",
    "visits": 1476,
    "diff": 52
  },
  {
    "date": "مارس 29، 2026",
    "visits": 1500,
    "diff": 24
  },
  {
    "date": "مارس 30، 2026",
    "visits": 1544,
    "diff": 44
  },
  {
    "date": "مارس 31، 2026",
    "visits": 1554,
    "diff": 10
  },
  {
    "date": "أفريل 01، 2026",
    "visits": 1606,
    "diff": 52
  },
  {
    "date": "أفريل 03، 2026",
    "visits": 1684,
    "diff": 78
  },
  {
    "date": "أفريل 04، 2026",
    "visits": 1694,
    "diff": 10
  },
  {
    "date": "أفريل 05، 2026",
    "visits": 1702,
    "diff": 8
  },
  {
    "date": "أفريل 06، 2026",
    "visits": 1707,
    "diff": 5
  },
  {
    "date": "أفريل 08، 2026",
    "visits": 1751,
    "diff": 44
  },
  {
    "date": "أفريل 09، 2026",
    "visits": 1766,
    "diff": 15
  },
  {
    "date": "أفريل 10، 2026",
    "visits": 1771,
    "diff": 5
  },
  {
    "date": "أفريل 11، 2026",
    "visits": 1772,
    "diff": 1
  },
  {
    "date": "أفريل 12، 2026",
    "visits": 1776,
    "diff": 4
  },
  {
    "date": "أفريل 13، 2026",
    "visits": 1777,
    "diff": 1
  },
  {
    "date": "أفريل 14، 2026",
    "visits": 1779,
    "diff": 2
  },
  {
    "date": "أفريل 15، 2026",
    "visits": 1783,
    "diff": 4
  },
  {
    "date": "أفريل 16، 2026",
    "visits": 1786,
    "diff": 3
  },
  {
    "date": "أفريل 17، 2026",
    "visits": 1788,
    "diff": 2
  },
  {
    "date": "أفريل 19، 2026",
    "visits": 1816,
    "diff": 28
  },
  {
    "date": "أفريل 20، 2026",
    "visits": 1820,
    "diff": 4
  },
  {
    "date": "أفريل 21، 2026",
    "visits": 1826,
    "diff": 6
  },
  {
    "date": "أفريل 22، 2026",
    "visits": 1829,
    "diff": 3
  },
  {
    "date": "أفريل 23، 2026",
    "visits": 1837,
    "diff": 8
  },
  {
    "date": "أفريل 24، 2026",
    "visits": 1839,
    "diff": 2
  },
  {
    "date": "أفريل 25، 2026",
    "visits": 1848,
    "diff": 9
  },
  {
    "date": "أفريل 26، 2026",
    "visits": 1861,
    "diff": 13
  },
  {
    "date": "أفريل 27، 2026",
    "visits": 1870,
    "diff": 9
  },
  {
    "date": "أفريل 28، 2026",
    "visits": 1876,
    "diff": 6
  },
  {
    "date": "أفريل 29، 2026",
    "visits": 1881,
    "diff": 5
  },
  {
    "date": "أفريل 30، 2026",
    "visits": 1883,
    "diff": 2
  },
  {
    "date": "ماي 01، 2026",
    "visits": 1890,
    "diff": 7
  },
  {
    "date": "ماي 02، 2026",
    "visits": 1892,
    "diff": 2
  },
  {
    "date": "ماي 03، 2026",
    "visits": 1895,
    "diff": 3
  },
  {
    "date": "ماي 04، 2026",
    "visits": 1897,
    "diff": 2
  },
  {
    "date": "ماي 05، 2026",
    "visits": 1897,
    "diff": 0
  },
  {
    "date": "ماي 06، 2026",
    "visits": 1899,
    "diff": 2
  },
  {
    "date": "ماي 07', 2026",
    "visits": 1900,
    "diff": 1
  },
  {
    "date": "ماي 08، 2026",
    "visits": 1902,
    "diff": 2
  },
  {
    "date": "ماي 09، 2026",
    "visits": 1908,
    "diff": 6
  },
  {
    "date": "ماي 10، 2026",
    "visits": 1912,
    "diff": 4
  },
  {
    "date": "ماي 11، 2026",
    "visits": 1916,
    "diff": 4
  },
  {
    "date": "ماي 12، 2026",
    "visits": 1917,
    "diff": 1
  },
  {
    "date": "ماي 13، 2026",
    "visits": 1919,
    "diff": 2
  },
  {
    "date": "ماي 14، 2026",
    "visits": 1920,
    "diff": 1
  },
  {
    "date": "ماي 15، 2026",
    "visits": 1927,
    "diff": 7
  },
  {
    "date": "ماي 16، 2026",
    "visits": 1930,
    "diff": 3
  },
  {
    "date": "ماي 17، 2026",
    "visits": 1931,
    "diff": 1
  },
  {
    "date": "ماي 18، 2026",
    "visits": 1936,
    "diff": 5
  },
  {
    "date": "ماي 19، 2026",
    "visits": 1938,
    "diff": 2
  },
  {
    "date": "ماي 20، 2026",
    "visits": 1938,
    "diff": 0
  },
  {
    "date": "ماي 21، 2026",
    "visits": 1944,
    "diff": 6
  },
  {
    "date": "ماي 22، 2026",
    "visits": 1945,
    "diff": 1
  },
  {
    "date": "ماي 23، 2026",
    "visits": 1948,
    "diff": 3
  },
  {
    "date": "ماي 24، 2026",
    "visits": 1949,
    "diff": 1
  },
  {
    "date": "ماي 25، 2026",
    "visits": 1954,
    "diff": 5
  },
  {
    "date": "ماي 26، 2026",
    "visits": 1955,
    "diff": 1
  },
  {
    "date": "ماي 27، 2026",
    "visits": 1957,
    "diff": 2
  },
  {
    "date": "ماي 28، 2026",
    "visits": 1961,
    "diff": 4
  },
  {
    "date": "ماي 29، 2026",
    "visits": 1962,
    "diff": 1
  },
  {
    "date": "ماي 30، 2026",
    "visits": 1965,
    "diff": 3
  },
  {
    "date": "ماي 31، 2026",
    "visits": 1967,
    "diff": 2
  },
  {
    "date": "جوان 01، 2026",
    "visits": 1970,
    "diff": 3
  },
  {
    "date": "جوان 02، 2026",
    "visits": 1974,
    "diff": 4
  },
  {
    "date": "جوان 03، 2026",
    "visits": 1977,
    "diff": 3
  },
  {
    "date": "جوان 04، 2026",
    "visits": 1980,
    "diff": 3
  },
  {
    "date": "جوان 05، 2026",
    "visits": 1983,
    "diff": 3
  },
  {
    "date": "جوان 06، 2026",
    "visits": 1985,
    "diff": 2
  },
  {
    "date": "جوان 07، 2026",
    "visits": 1985,
    "diff": 0
  },
  {
    "date": "جوان 08، 2026",
    "visits": 1987,
    "diff": 2
  },
  {
    "date": "جوان 09، 2026",
    "visits": 1988,
    "diff": 1
  },
  {
    "date": "جوان 10، 2026",
    "visits": 1990,
    "diff": 2
  },
  {
    "date": "جوان 11، 2026",
    "visits": 1993,
    "diff": 3
  },
  {
    "date": "جوان 12، 2026",
    "visits": 1998,
    "diff": 5
  },
  {
    "date": "جوان 14، 2026",
    "visits": 2020,
    "diff": 22
  },
  {
    "date": "جوان 15، 2026",
    "visits": 2021,
    "diff": 1
  },
  {
    "date": "جوان 16، 2026",
    "visits": 2025,
    "diff": 4
  },
  {
    "date": "جوان 17، 2026",
    "visits": 2025,
    "diff": 0
  },
  {
    "date": "جوان 19، 2026",
    "visits": 2040,
    "diff": 15
  },
  {
    "date": "جوان 20، 2026",
    "visits": 2046,
    "diff": 6
  },
  {
    "date": "جوان 21، 2026",
    "visits": 2049,
    "diff": 3
  },
  {
    "date": "جوان 22، 2026",
    "visits": 2049,
    "diff": 0
  },
  {
    "date": "جوان 26، 2026",
    "visits": 2101,
    "diff": 2101
  },
  {
    "date": "جوان 26، 2026",
    "visits": 2106,
    "diff": 5
  }
]